indicator_syncthing/__init__.py
indicator_syncthing/__main__.py
indicator_syncthing/icons/icon.png
indicator_syncthing/icons/syncthing-client-down.png
indicator_syncthing/icons/syncthing-client-down.svg
indicator_syncthing/icons/syncthing-client-error.png
indicator_syncthing/icons/syncthing-client-error.svg
indicator_syncthing/icons/syncthing-client-idle.png
indicator_syncthing/icons/syncthing-client-idle.svg
indicator_syncthing/icons/syncthing-client-paused.png
indicator_syncthing/icons/syncthing-client-paused.svg
indicator_syncthing/icons/syncthing-client-scanning.png
indicator_syncthing/icons/syncthing-client-scanning.svg
indicator_syncthing/icons/syncthing-client-up.png
indicator_syncthing/icons/syncthing-client-up.svg
indicator_syncthing/icons/syncthing-client-updating.png
indicator_syncthing/icons/syncthing-client-updating.svg
indicator_syncthing/icons/syncthing-client-updown.png
indicator_syncthing/icons/syncthing-client-updown.svg
indicator_syncthing-0.1.0.data/data/share/applications/indicator-syncthing.desktop
indicator_syncthing-0.1.0.dist-info/LICENSE
indicator_syncthing-0.1.0.dist-info/METADATA
indicator_syncthing-0.1.0.dist-info/WHEEL
indicator_syncthing-0.1.0.dist-info/entry_points.txt
indicator_syncthing-0.1.0.dist-info/top_level.txt
indicator_syncthing-0.1.0.dist-info/RECORD
