Metadata-Version: 2.1
Name: indicator-syncthing
Version: 0.1.0
Summary: A Syncthing status menu for Unity and other desktops that support AppIndicator.
Home-page: https://github.com/domdfcoding/indicator-syncthing
Author: Dominic Davis-Foster
Author-email: dominic@davis-foster.co.uk
License: Apache Software License
Project-URL: Documentation, https://indicator-syncthing.readthedocs.io
Project-URL: Issue Tracker, https://github.com/domdfcoding/indicator-syncthing/issues
Project-URL: Source Code, https://github.com/domdfcoding/indicator-syncthing
Platform: UNKNOWN
Classifier: Development Status :: 4 - Beta
Classifier: Intended Audience :: End Users/Desktop
Classifier: License :: OSI Approved :: Apache Software License
Classifier: Operating System :: POSIX :: Linux
Classifier: Programming Language :: Python
Classifier: Programming Language :: Python :: 3 :: Only
Classifier: Programming Language :: Python :: 3.6
Classifier: Programming Language :: Python :: 3.7
Classifier: Programming Language :: Python :: 3.8
Classifier: Programming Language :: Python :: Implementation :: CPython
Classifier: Topic :: Utilities
Requires-Python: >=3.6
Requires-Dist: python-dateutil (>=2.8.0)
Requires-Dist: requests-futures (>=1.0.0)
Requires-Dist: requests (>=2.18.0)
Requires-Dist: PyGObject (>=3.34.0)
Provides-Extra: all
